publsp/__init__.py
publsp/api/__init__.py
publsp/api/app.py
publsp/api/routes/__init__.py
publsp/api/routes/ads.py
publsp/api/routes/channels.py
publsp/api/routes/orders.py
publsp/api/routes/session.py
publsp/api/session.py
publsp/api/utils.py
publsp/blip51/channel.py
publsp/blip51/info.py
publsp/blip51/mixins.py
publsp/blip51/order.py
publsp/blip51/payment.py
publsp/blip51/utils.py
publsp/cli/basecli.py
publsp/cli/customerargs.py
publsp/cli/customercli.py
publsp/cli/helpers.py
publsp/cli/logger.py
publsp/cli/lspargs.py
publsp/cli/lspcli.py
publsp/cli/lsputils.py
publsp/ln/base.py
publsp/ln/bech32.py
publsp/ln/cln.py
publsp/ln/invdecoder.py
publsp/ln/lnd.py
publsp/ln/requesthandlers.py
publsp/ln/utils.py
publsp/main.py
publsp/marketplace/base.py
publsp/marketplace/customer.py
publsp/marketplace/lsp.py
publsp/marketplace/response_manager.py
publsp/nostr/client.py
publsp/nostr/keyhandler.py
publsp/nostr/kinds.py
publsp/nostr/nip17.py
publsp/nostr/relays.py
publsp/settings.py
publsp-0.4.19.dist-info/LICENSE
publsp-0.4.19.dist-info/METADATA
publsp-0.4.19.dist-info/WHEEL
publsp-0.4.19.dist-info/entry_points.txt
publsp-0.4.19.dist-info/RECORD
