Metadata-Version: 2.3
Name: publsp
Version: 0.4.19
Summary: A rough implementation of the bLIP51, inspired by NIP-15/69/99 spec mediated through Nostr
License: MIT
Author: smallworlnd
Author-email: smallworlnd@sparkseer.space
Requires-Python: >=3.10,<4
Classifier: License :: OSI Approved :: MIT License
Classifier: Programming Language :: Python :: 3
Classifier: Programming Language :: Python :: 3.10
Classifier: Programming Language :: Python :: 3.11
Classifier: Programming Language :: Python :: 3.12
Classifier: Programming Language :: Python :: 3.13
Requires-Dist: bitstring (>=4.3.0,<5.0.0)
Requires-Dist: click (>=8.1.8,<9.0.0)
Requires-Dist: dotenv (>=0.9.9,<0.10.0)
Requires-Dist: dumb-init (>=1.2.5.post1,<2.0.0)
Requires-Dist: fastapi (>=0.115.12,<0.116.0)
Requires-Dist: httpx (>=0.28.1,<0.29.0)
Requires-Dist: nostr-sdk (>=0.40.0,<=0.42.1)
Requires-Dist: pydantic (>=2.10.6,<3.0.0)
Requires-Dist: pydantic-settings (>=2.8.1,<3.0.0)
Requires-Dist: secp256k1 (>=0.14.0,<0.15.0)
Requires-Dist: uvicorn (>=0.34.2,<0.35.0)
